speech_dataset_converter_cli/__init__.py
speech_dataset_converter_cli/argparse_helper.py
speech_dataset_converter_cli/cli.py
speech_dataset_converter_cli/convert_l2arctic.py
speech_dataset_converter_cli/convert_ljs.py
speech_dataset_converter_cli/convert_thchs_cslt.py
speech_dataset_converter_cli/convert_thchs_slr.py
speech_dataset_converter_cli/logging_configuration.py
speech_dataset_converter_cli/restore_directory_structure.py
speech_dataset_converter_cli/utils.py
speech_dataset_parser/__init__.py
speech_dataset_parser/parse.py
speech_dataset_parser/types.py
speech_dataset_parser/utils.py
speech_dataset_parser-0.0.4.dist-info/LICENSE
speech_dataset_parser-0.0.4.dist-info/METADATA
speech_dataset_parser-0.0.4.dist-info/WHEEL
speech_dataset_parser-0.0.4.dist-info/entry_points.txt
speech_dataset_parser-0.0.4.dist-info/top_level.txt
speech_dataset_parser-0.0.4.dist-info/RECORD
