Metadata-Version: 2.1
Name: speech-dataset-parser
Version: 0.0.4
Summary: Library to parse speech datasets stored in a generic format based on TextGrids. A tool (CLI) for converting common datasets like LJ Speech into a generic format is included.
Author-email: Stefan Taubert <pypi@stefantaubert.com>
Maintainer-email: Stefan Taubert <pypi@stefantaubert.com>
License: MIT
Project-URL: Homepage, https://github.com/stefantaubert/speech-dataset-parser
Project-URL: Issues, https://github.com/stefantaubert/speech-dataset-parser/issues
Keywords: Text-to-speech,Speech synthesis,Corpus,Utils,Language,Linguistics
Classifier: Development Status :: 2 - Pre-Alpha
Classifier: Operating System :: OS Independent
Classifier: Operating System :: MacOS
Classifier: Operating System :: POSIX
Classifier: Operating System :: POSIX :: BSD
Classifier: Operating System :: POSIX :: Linux
Classifier: Operating System :: Unix
Classifier: Operating System :: Microsoft :: Windows
Classifier: Programming Language :: Python
Classifier: Programming Language :: Python :: 3
Classifier: Programming Language :: Python :: 3.7
Classifier: Programming Language :: Python :: 3.8
Classifier: Programming Language :: Python :: 3.9
Classifier: Programming Language :: Python :: 3.10
Classifier: Programming Language :: Python :: 3.11
Classifier: License :: OSI Approved :: MIT License
Requires-Python: <4,>=3.7
License-File: LICENSE
Requires-Dist: tqdm
Requires-Dist: TextGrid (>=1.5)
Requires-Dist: ordered-set (>=4.1.0)
Requires-Dist: importlib-resources ; python_version < "3.8"
